<!DOCTYPE plugin PUBLIC "-//JPF//Java Plug-in Manifest 1.0" "http://jpf.sourceforge.net/plugin_1_0.dtd">
<plugin id="com.tle.web.viewitem.largeimageviewer" version="1">
	<requires>
		<import plugin-id="com.tle.common.i18n" />
		<import plugin-id="com.tle.core.config" />
		<import plugin-id="com.tle.core.guice" />
		<import plugin-id="com.tle.core.imagemagick" />
		<import plugin-id="com.tle.web.sections" />
		<import plugin-id="com.tle.web.sections.equella" />
		<import plugin-id="com.tle.web.wizard" />
		<import plugin-id="com.tle.web.viewurl" />
		<import plugin-id="com.tle.web.viewitem" />
	</requires>

	<runtime>
		<library type="code" path="classes/" id="core" />
		<library type="resources" path="resources/" id="resources" />
	</runtime>

	<extension plugin-id="com.tle.core.guice" point-id="module" id="guiceModules">
		<parameter id="class" value="com.tle.web.sections.equella.guice.EquellaModule" />
		<parameter id="class" value="com.tle.web.viewitem.largeimageviewer.guice.LargeImageViewerModule" />
	</extension>


	<extension plugin-id="com.tle.web.sections" point-id="section" id="largeImageSection">
		<parameter id="class" value="bean:com.tle.web.viewitem.largeimageviewer.LargeImageViewerSection" />
		<parameter id="path" value="/viewitem/viewitem" />
		<parameter id="parentid" value="" />
	</extension>

	<extension plugin-id="com.tle.common.i18n" point-id="bundle" id="strings">
		<parameter id="group" value="resource-centre" />
		<parameter id="file" value="lang/i18n.properties" />
	</extension>

	<extension plugin-id="com.tle.web.viewurl" point-id="resourceViewer" id="livNavTreeViewer">
		<parameter id="id" value="livNavTreeViewer" />
		<parameter id="nameKey" value="com.tle.web.viewitem.largeimageviewer.navviewer.title" />
		<parameter id="linkKey" value="com.tle.web.viewitem.largeimageviewer.button.title" />
		<parameter id="class" value="bean:com.tle.web.viewitem.largeimageviewer.LargeImageViewer" />
	</extension>

	<extension plugin-id="com.tle.web.sections" point-id="section" id="tileAfterContributionSection">
		<parameter id="class" value="bean:com.tle.web.viewitem.largeimageviewer.TileAfterContributionSection" />
		<parameter id="path" value="/access/runwizard" />
		<parameter id="parentid" value="WIZARD_NAVIGATION" />
	</extension>
</plugin>
